clearconsole/__init__.py
clearconsole/clearconsole.py
clearconsole-0.0.5.dist-info/LICENCE
clearconsole-0.0.5.dist-info/METADATA
clearconsole-0.0.5.dist-info/WHEEL
clearconsole-0.0.5.dist-info/top_level.txt
clearconsole-0.0.5.dist-info/RECORD
