Metadata-Version: 2.1
Name: clearconsole
Version: 0.0.5
Summary: Can be used to clear the screen.
Home-page: https://github.com/mathstar13/clear
Author: greatusername
Author-email: alexander.destefano@gmail.com
License: UNKNOWN
Platform: UNKNOWN
Classifier: Programming Language :: Python :: 3
Classifier: License :: OSI Approved :: MIT License
Classifier: Operating System :: OS Independent
Requires-Python: >=3.1
